[{"__type__":"cc.Prefab","data":{"__id__":1}},{"__type__":"cc.Node","_name":"Line_Start","_components":[{"__type__":"cc.ModelComponent","_name":"Sphere<ModelComponent>","node":{"__id__":1},"_materials":[{"__uuid__":"0b29x25HRIYLOtM1dnxSaX"}],"lightmapSettings":{"__type__":"cc.ModelLightmapSettings"},"_mesh":{"__uuid__":"12Y9dMgWdJKJGmTiZyQR9H@17020"}}],"_prefab":{"__type__":"cc.PrefabInfo","root":{"__id__":1},"asset":{"__id__":0},"fileId":"d2z0iU8CJG8qtbCeiwQYlp","_synced":{"default":false,"serializable":false}}}]
